.gitignore
LICENSE
README.rst
setup.py
comments_moderation/__init__.py
comments_moderation/admin.py
comments_moderation/filtered_moderator.py
comments_moderation/models.py
comments_moderation/moderation_modes.py
comments_moderation/settings.py
comments_moderation/locale/cs_CZ/LC_MESSAGES/django.po
comments_moderation/south_migrations/0001_initial.py
comments_moderation/south_migrations/0002_auto__chg_field_emailfilter_active.py
comments_moderation/south_migrations/__init__.py
django_comments_moderation.egg-info/PKG-INFO
django_comments_moderation.egg-info/SOURCES.txt
django_comments_moderation.egg-info/dependency_links.txt
django_comments_moderation.egg-info/not-zip-safe
django_comments_moderation.egg-info/requires.txt
django_comments_moderation.egg-info/top_level.txt