Metadata-Version: 1.1
Name: django-comments-moderation
Version: 1.0
Summary: Moderation plugin for django-fluent-comments
Home-page: https://github.com/PetrDlouhy/django-comments-moderation
Author: Petr Dlouhý
Author-email: petr.dlouhy@email.cz
License: GNU Affero General Public License, Version 3.0
Platform: UNKNOWN
Classifier: Development Status :: 4 - Beta
Classifier: Environment :: Web Environment
Classifier: Framework :: Django
Classifier: Intended Audience :: Developers
Classifier: License :: OSI Approved :: GNU Affero General Public License v3
Classifier: Operating System :: OS Independent
Classifier: Programming Language :: Python
Classifier: Programming Language :: Python :: 2.6
Classifier: Programming Language :: Python :: 2.7
Classifier: Topic :: Internet :: WWW/HTTP
Classifier: Topic :: Internet :: WWW/HTTP :: Dynamic Content
Classifier: Topic :: Software Development :: Libraries :: Application Frameworks
Classifier: Topic :: Software Development :: Libraries :: Python Modules
Requires: Django (>=1.3)
